nvidia/__init__.py
nvidia/cuda_cccl/__init__.py
nvidia/cuda_cccl/bin/__init__.py
nvidia/cuda_cccl/include/__init__.py
nvidia/cuda_cccl/include/cub/config.cuh
nvidia/cuda_cccl/include/cub/cub.cuh
nvidia/cuda_cccl/include/cub/util_allocator.cuh
nvidia/cuda_cccl/include/cub/util_arch.cuh
nvidia/cuda_cccl/include/cub/util_compiler.cuh
nvidia/cuda_cccl/include/cub/util_cpp_dialect.cuh
nvidia/cuda_cccl/include/cub/util_debug.cuh
nvidia/cuda_cccl/include/cub/util_deprecated.cuh
nvidia/cuda_cccl/include/cub/util_device.cuh
nvidia/cuda_cccl/include/cub/util_macro.cuh
nvidia/cuda_cccl/include/cub/util_math.cuh
nvidia/cuda_cccl/include/cub/util_namespace.cuh
nvidia/cuda_cccl/include/cub/util_ptx.cuh
nvidia/cuda_cccl/include/cub/util_type.cuh
nvidia/cuda_cccl/include/cub/version.cuh
nvidia/cuda_cccl/include/cub/agent/agent_histogram.cuh
nvidia/cuda_cccl/include/cub/agent/agent_merge_sort.cuh
nvidia/cuda_cccl/include/cub/agent/agent_radix_sort_downsweep.cuh
nvidia/cuda_cccl/include/cub/agent/agent_radix_sort_histogram.cuh
nvidia/cuda_cccl/include/cub/agent/agent_radix_sort_onesweep.cuh
nvidia/cuda_cccl/include/cub/agent/agent_radix_sort_upsweep.cuh
nvidia/cuda_cccl/include/cub/agent/agent_reduce.cuh
nvidia/cuda_cccl/include/cub/agent/agent_reduce_by_key.cuh
nvidia/cuda_cccl/include/cub/agent/agent_rle.cuh
nvidia/cuda_cccl/include/cub/agent/agent_scan.cuh
nvidia/cuda_cccl/include/cub/agent/agent_scan_by_key.cuh
nvidia/cuda_cccl/include/cub/agent/agent_segment_fixup.cuh
nvidia/cuda_cccl/include/cub/agent/agent_segmented_radix_sort.cuh
nvidia/cuda_cccl/include/cub/agent/agent_select_if.cuh
nvidia/cuda_cccl/include/cub/agent/agent_spmv_orig.cuh
nvidia/cuda_cccl/include/cub/agent/agent_sub_warp_merge_sort.cuh
nvidia/cuda_cccl/include/cub/agent/agent_three_way_partition.cuh
nvidia/cuda_cccl/include/cub/agent/single_pass_scan_operators.cuh
nvidia/cuda_cccl/include/cub/block/block_adjacent_difference.cuh
nvidia/cuda_cccl/include/cub/block/block_discontinuity.cuh
nvidia_cuda_cccl_cu11-11.8.89.post1.dist-info/License.txt
nvidia_cuda_cccl_cu11-11.8.89.post1.dist-info/METADATA
nvidia_cuda_cccl_cu11-11.8.89.post1.dist-info/WHEEL
nvidia_cuda_cccl_cu11-11.8.89.post1.dist-info/top_level.txt
nvidia_cuda_cccl_cu11-11.8.89.post1.dist-info/RECORD
